pyresdev/__init__.py
pyresdev/db/MySQL_db_connection.py
pyresdev/db/__init__.py
pyresdev/dbprocessing/__init__.py
pyresdev/dbprocessing/databricks_training_processing.py
pyresdev/processing/L700_utils.py
pyresdev/processing/__init__.py
pyresdev/processing/predictions_processing.py
pyresdev/processing/processing.py
pyresdev/utils/__init__.py
pyresdev/utils/aws_tools.py
pyresdev/utils/batch_transform_tools.py
pyresdev/utils/data_engineering_functions.py
pyresdev/utils/general_functions.py
pyresdev/utils/memory_reduction.py
pyresdev/utils/old_functions.py
rating/__init__.py
rating/DBProcessing/__init__.py
rating/DBProcessing/databricks_training_processing.py
rating/databricks_processing/__init__.py
rating/databricks_processing/databricks_training_processing.py
rating/db/MySQL_db_connection.py
rating/db/__init__.py
rating/processing/__init__.py
rating/processing/databricks_training_processing.py
rating/processing/predictions_processing.py
rating/processing/processing.py
rating/utils/__init__.py
rating/utils/aws_tools.py
rating/utils/batch_transform_tools.py
rating/utils/data_engineering_functions.py
rating/utils/general_functions.py
rating/utils/memory_reduction.py
rating/utils/old_functions.py
pyresdev-0.2.37.dist-info/LICENSE.txt
pyresdev-0.2.37.dist-info/METADATA
pyresdev-0.2.37.dist-info/WHEEL
pyresdev-0.2.37.dist-info/top_level.txt
pyresdev-0.2.37.dist-info/RECORD
