Metadata-Version: 2.1
Name: pyresdev
Version: 0.2.37
Summary: Bairesdev package used in DS
Home-page: UNKNOWN
Author: Patricio Massaro
Author-email: patricio.massaro@bairesdev.com
License: MIT
Platform: UNKNOWN
Classifier: License :: OSI Approved :: MIT License
Classifier: Programming Language :: Python :: 3
Classifier: Programming Language :: Python :: 3.8
License-File: LICENSE.txt
Requires-Dist: numpy
Requires-Dist: pandas
Requires-Dist: regex
Requires-Dist: sqlalchemy
